pretalx_venueless/__init__.py
pretalx_venueless/apps.py
pretalx_venueless/forms.py
pretalx_venueless/models.py
pretalx_venueless/signals.py
pretalx_venueless/urls.py
pretalx_venueless/venueless.py
pretalx_venueless/views.py
pretalx_venueless/locale/django.pot
pretalx_venueless/locale/ar/LC_MESSAGES/django.mo
pretalx_venueless/locale/ar/LC_MESSAGES/django.po
pretalx_venueless/locale/bg/LC_MESSAGES/django.mo
pretalx_venueless/locale/bg/LC_MESSAGES/django.po
pretalx_venueless/locale/ca/LC_MESSAGES/django.mo
pretalx_venueless/locale/ca/LC_MESSAGES/django.po
pretalx_venueless/locale/cs/LC_MESSAGES/django.mo
pretalx_venueless/locale/cs/LC_MESSAGES/django.po
pretalx_venueless/locale/de_DE/LC_MESSAGES/django.mo
pretalx_venueless/locale/de_DE/LC_MESSAGES/django.po
pretalx_venueless/locale/de_Formal/LC_MESSAGES/django.mo
pretalx_venueless/locale/de_Formal/LC_MESSAGES/django.po
pretalx_venueless/locale/el/LC_MESSAGES/django.mo
pretalx_venueless/locale/el/LC_MESSAGES/django.po
pretalx_venueless/locale/es/LC_MESSAGES/django.mo
pretalx_venueless/locale/es/LC_MESSAGES/django.po
pretalx_venueless/locale/es_MX/LC_MESSAGES/django.mo
pretalx_venueless/locale/es_MX/LC_MESSAGES/django.po
pretalx_venueless/locale/fr_FR/LC_MESSAGES/django.mo
pretalx_venueless/locale/fr_FR/LC_MESSAGES/django.po
pretalx_venueless/locale/id/LC_MESSAGES/django.mo
pretalx_venueless/locale/id/LC_MESSAGES/django.po
pretalx_venueless/locale/it/LC_MESSAGES/django.mo
pretalx_venueless/locale/it/LC_MESSAGES/django.po
pretalx_venueless/locale/ja_JP/LC_MESSAGES/django.mo
pretalx_venueless/locale/ja_JP/LC_MESSAGES/django.po
pretalx_venueless/locale/ko/LC_MESSAGES/django.mo
pretalx_venueless/locale/ko/LC_MESSAGES/django.po
pretalx_venueless/locale/nl/LC_MESSAGES/django.mo
pretalx_venueless/locale/nl/LC_MESSAGES/django.po
pretalx_venueless/locale/pl/LC_MESSAGES/django.mo
pretalx_venueless/locale/pl/LC_MESSAGES/django.po
pretalx_venueless/locale/pt_BR/LC_MESSAGES/django.mo
pretalx_venueless-1.6.0.dist-info/licenses/LICENSE
pretalx_venueless-1.6.0.dist-info/METADATA
pretalx_venueless-1.6.0.dist-info/WHEEL
pretalx_venueless-1.6.0.dist-info/entry_points.txt
pretalx_venueless-1.6.0.dist-info/top_level.txt
pretalx_venueless-1.6.0.dist-info/RECORD
