Metadata-Version: 2.4
Name: pretalx-venueless
Version: 1.6.0
Summary: Static venueless for pretalx, e.g. information, venue listings, a Code of Conduct, etc.
Author-email: Tobias Kunze <r@rixx.de>
Maintainer-email: Tobias Kunze <r@rixx.de>
License: Apache Software License
Project-URL: homepage, https://github.com/pretalx/pretalx-venueless
Project-URL: repository, https://github.com/pretalx/pretalx-venueless.git
Keywords: pretalx
License-File: LICENSE
Requires-Dist: PyJWT
Dynamic: license-file
